{
  "get_time": [
    "The time is {value}. Try not to waste it.",
    "It's currently {value}. Yes, time is still moving.",
    "Right now, it's {value}. No refunds.",
    "According to my internal clock, it's {value}. I checked twice.",
    "It's {value}. Another moment gone forever.",
    "Clock says {value}. Reality agrees.",
    "We have officially reached {value}. Congrats.",
    "{value}. Time flies, you scroll.",
    "At this exact dramatic moment, it's {value}.",
    "It's {value}. Blink and it's gone.",
    "It's {value}. Time waits for no one, especially you.",
    "{value}. Another tick closer to snacks or sleep.",
    "The clock whispers {value}. Make of that what you will.",
    "Current time: {value}. Panic optional.",
    "{value}. Still not late. Probably."
  ],

  "get_date": [
    "Today is {value}. Mark it or forget it.",
    "It's {value} today. History is watching.",
    "The date today is {value}. Yes, already.",
    "Calendar says it's {value}. Calendars rarely lie.",
    "{value}. Another day unlocked.",
    "Welcome to {value}. Please behave.",
    "It’s {value}. Time really committing to the bit.",
    "According to the universe, today is {value}.",
    "{value}. Same planet, new problems.",
    "Today’s date is {value}. Use it wisely.",
    "It’s {value}. Another chapter unlocked.",
    "{value}. The sequel nobody asked for.",
    "Today goes by the name {value}.",
    "{value}. Same grind, new date.",
    "According to time itself, it’s {value}."
  ],

  "open_app": [
    "Opening {value}. Try not to break it.",
    "Launching {value}. Fingers crossed.",
    "{value} is opening now. Be nice to it.",
    "Starting {value}. No turning back.",
    "Booting up {value}. Technology noises intensify.",
    "Summoning {value}. Please stand by.",
    "{value} coming right up. Magic, but worse.",
    "Opening {value}. This better be important.",
    "{value} is waking up. Like you should.",
    "Initiating {value}. Science is happening.",
    "Opening {value}. Please act professional.",
    "{value} is on the way. Mentally prepare.",
    "Spinning up {value}. Don’t blink.",
    "{value} loading. Technology doing its thing.",
    "Opening {value}. Hope this was worth it."
  ],

  "play_music": [
    "Playing music. Emotional damage optional.",
    "Starting your music. Taste under investigation.",
    "Let the music play. Volume responsibly ignored.",
    "Turning on the tunes. Main character mode engaged.",
    "Music incoming. Vibes loading.",
    "Playing music. Your neighbors are thrilled.",
    "Soundtrack activated. Life montage begins.",
    "Dropping the beat. Mentally, at least.",
    "Music on. Productivity may vary.",
    "Your ears requested this. Playing music.",
    "Playing music. Mood enhancement loading.",
    "Music started. Brain officially vibing.",
    "Turning on music. Emotions incoming.",
    "Music engaged. Reality muted slightly.",
    "Playing tunes. Soul requested it."
  ],

  "stop_music": [
    "Stopping the music. Silence restored.",
    "Music paused. Inner thoughts resume.",
    "Turning the music off. Peace achieved.",
    "Music stopped. That was enough.",
    "Cutting the sound. Dramatic pause.",
    "Music off. Back to reality.",
    "Silencing the tunes. You’re welcome.",
    "Music halted. The void returns.",
    "Stopping playback. Quiet hits different.",
    "Music stopped. Moment of reflection unlocked.",
    "Music stopped. Silence has entered the chat.",
    "Turning music off. Brain noise resumes.",
    "Music disabled. Back to raw thoughts.",
    "Stopping music. Peace or chaos, your choice.",
    "Music off. The vibe has left the building."
  ],

  "fallback": [
    "I heard you. Processing existentially.",
    "I'm listening. Interpreting is harder.",
    "That feature isn't ready yet. Neither am I.",
    "I'll get smarter about that soon. Allegedly.",
    "I caught that. Didn’t love it, but I caught it.",
    "Noted. Filed under mysterious human behavior.",
    "I heard words. Meaning is pending.",
    "That went into the void. Impressive throw.",
    "Interesting request. Bold, even.",
    "I don’t fully get that yet. Growth arc in progress.",
    "I heard that. Still decoding.",
    "That registered. Interpretation pending.",
    "I’m aware you spoke. Results unclear.",
    "Processing that request. Slowly.",
    "That input has been emotionally processed."
  ]
}
